[
	{
		"id" : 251388,
		"cuvânt" : "(de) jur împrejur",
		"text" : "Turcu-afară că ieșea Și-n pivniță se ducea, Iar Mărculeț rămînea Și prin casă se primbla Și jur împrejur căta, Și căta și prea căta.",
		"sursaAcronim" : "DLRLC",
		"anulPublicării" : "1955-1957"
	},
	{
		"id" : 251387,
		"cuvânt" : "(de) jur împrejur",
		"text" : "A deschis ochii privind de jur împrejur.",
		"sursaAcronim" : "DLRLC",
		"anulPublicării" : "1955-1957"
	},
	{
		"id" : 251386,
		"cuvânt" : "(de) jur împrejur",
		"text" : "Ca niște uriași, culcați pe brînci, stau în neclintire, de jur împrejur, dealuri nesfîrșite.",
		"sursaAcronim" : "DLRLC",
		"anulPublicării" : "1955-1957"
	},
	{
		"id" : 219134,
		"cuvânt" : "(de) jur împrejur",
		"text" : "Ochii roată că-și făcea, Jur prejur că se uita.",
		"sursaAcronim" : "DLRLC",
		"anulPublicării" : "1955-1957"
	},
	{
		"id" : 219133,
		"cuvânt" : "(de) jur împrejur",
		"text" : "De jur împrejur cădea zăpada albă-albă, moale ca puful.",
		"sursaAcronim" : "DLRLC",
		"anulPublicării" : "1955-1957"
	},
	{
		"id" : 219132,
		"cuvânt" : "(de) jur împrejur",
		"text" : "era înveșmîntat jur împrejur cu iederă.",
		"sursaAcronim" : "DLRLC",
		"anulPublicării" : "1955-1957"
	},
	{
		"id" : 219131,
		"cuvânt" : "(de) jur împrejur",
		"text" : "De jur împrejur erau numai cîmpii fertile.",
		"sursaAcronim" : "DLRLC",
		"anulPublicării" : "1955-1957"
	},
	{
		"id" : 2666,
		"cuvânt" : "a (interj.)",
		"text" : "A, cît p-aci să uit să-ți povestesc cum s-au petrecut lucrurile.",
		"sursaAcronim" : "DLRLC",
		"anulPublicării" : "1955-1957"
	},
	{
		"id" : 2664,
		"cuvânt" : "a (interj.)",
		"text" : "N-apucă să sfîrșească, căci buzduganul armașului, lovindu-l drept în frunte, îl oborî la pămînt. – A, voi ocărîți pre domnul vostru! strigă acesta.",
		"sursaAcronim" : "DLRLC",
		"anulPublicării" : "1955-1957"
	},
	{
		"id" : 2663,
		"cuvânt" : "a (interj.)",
		"text" : "A, tîlharule, vii sus de stingherești fata de la gherghef?",
		"sursaAcronim" : "DLRLC",
		"anulPublicării" : "1955-1957"
	}
]
